feffery_dash_utils/__init__.py
feffery_dash_utils/component_prop_utils/__init__.py
feffery_dash_utils/component_prop_utils/to_box_data.py
feffery_dash_utils/i18n_utils/__init__.py
feffery_dash_utils/style_utils/__init__.py
feffery_dash_utils/style_utils/style.py
feffery_dash_utils/template_utils/__init__.py
feffery_dash_utils/template_utils/dashboard_components/__init__.py
feffery_dash_utils/tree_utils/__init__.py
feffery_dash_utils/tree_utils/tree_manager.py
feffery_dash_utils/version_utils/__init__.py
feffery_dash_utils-0.2.6.dist-info/licenses/LICENSE
tests/__init__.py
tests/style_utils/__init__.py
tests/style_utils/style_tests.py
tests/tree_utils/__init__.py
tests/tree_utils/tree_manager_tests.py
feffery_dash_utils-0.2.6.dist-info/METADATA
feffery_dash_utils-0.2.6.dist-info/WHEEL
feffery_dash_utils-0.2.6.dist-info/top_level.txt
feffery_dash_utils-0.2.6.dist-info/RECORD
