Metadata-Version: 2.4
Name: feffery_dash_utils
Version: 0.2.6
Summary: A series of tool functions to assist Dash application development.
Home-page: https://github.com/CNFeffery/feffery-dash-utils
Author: CNFeffery <fefferypzy@gmail.com>
Author-email: fefferypzy@gmail.com
License: MIT
Classifier: Framework :: Dash
Requires-Python: >=3.8
License-File: LICENSE
Requires-Dist: cssutils
Requires-Dist: packaging
Dynamic: author
Dynamic: author-email
Dynamic: classifier
Dynamic: description
Dynamic: description-content-type
Dynamic: home-page
Dynamic: license
Dynamic: license-file
Dynamic: requires-dist
Dynamic: requires-python
Dynamic: summary
